topo_map_processor/__init__.py
topo_map_processor/_version.py
topo_map_processor/processor.py
topo_map_processor/tools/__init__.py
topo_map_processor/tools/collect_bounds.py
topo_map_processor/tools/create_force_redo_bounds.py
topo_map_processor/tools/retile.py
topo_map_processor/tools/retile_e2e.py
topo_map_processor/tools/tile.py
topo_map_processor/tools/utils.py
topo_map_processor-0.1.22.dist-info/METADATA
topo_map_processor-0.1.22.dist-info/WHEEL
topo_map_processor-0.1.22.dist-info/entry_points.txt
topo_map_processor-0.1.22.dist-info/licenses/LICENSE
topo_map_processor-0.1.22.dist-info/RECORD
