Metadata-Version: 2.4
Name: topo_map_processor
Version: 0.1.22
Summary: Library for processing topographic maps
Project-URL: homepage, https://github.com/ramSeraph/topo_map_processor
Project-URL: repository, https://github.com/ramSeraph/topo_map_processor.git
Author-email: Sreeram Kandimalla <kandimalla.sreeram@gmail.com>
License: This is free and unencumbered software released into the public domain.
License-File: LICENSE
Requires-Python: >=3.12
Requires-Dist: gh-release-tools>=0.1.12
Requires-Dist: mercantile>=1.2.1
Requires-Dist: pmtiles-mosaic>=0.1.0
Requires-Dist: requests>=2.32.4
Requires-Dist: shapely>=2.1.1
Provides-Extra: easyocr
Requires-Dist: easyocr>=1.7.2; extra == 'easyocr'
Provides-Extra: parse
Requires-Dist: imgcat>=0.6.0; extra == 'parse'
Requires-Dist: numpy>=2.3.1; extra == 'parse'
Requires-Dist: opencv-python-headless>=4.11.0.86; extra == 'parse'
Requires-Dist: pillow>=11.3.0; extra == 'parse'
Requires-Dist: pyproj>=3.7.1; extra == 'parse'
Requires-Dist: pytesseract>=0.3.13; extra == 'parse'
Requires-Dist: rasterio>=1.4.3; extra == 'parse'
Provides-Extra: pinned
Requires-Dist: aiofiles==24.1.0; extra == 'pinned'
Requires-Dist: aiohappyeyeballs==2.6.1; extra == 'pinned'
Requires-Dist: aiohttp==3.12.15; extra == 'pinned'
Requires-Dist: aiosignal==1.4.0; extra == 'pinned'
Requires-Dist: attrs==25.3.0; extra == 'pinned'
Requires-Dist: certifi==2025.8.3; extra == 'pinned'
Requires-Dist: charset-normalizer==3.4.3; extra == 'pinned'
Requires-Dist: click==8.3.0; extra == 'pinned'
Requires-Dist: colorama==0.4.6; (sys_platform == 'win32') and extra == 'pinned'
Requires-Dist: colorlog==6.9.0; extra == 'pinned'
Requires-Dist: frozenlist==1.7.0; extra == 'pinned'
Requires-Dist: gh-release-tools==0.1.12; extra == 'pinned'
Requires-Dist: idna==3.10; extra == 'pinned'
Requires-Dist: mercantile==1.2.1; extra == 'pinned'
Requires-Dist: multidict==6.6.4; extra == 'pinned'
Requires-Dist: numpy==2.3.3; extra == 'pinned'
Requires-Dist: pillow==11.3.0; extra == 'pinned'
Requires-Dist: pmtiles-mosaic==0.1.5; extra == 'pinned'
Requires-Dist: pmtiles==3.4.1; extra == 'pinned'
Requires-Dist: propcache==0.3.2; extra == 'pinned'
Requires-Dist: pypdl==1.5.6; extra == 'pinned'
Requires-Dist: requests==2.32.5; extra == 'pinned'
Requires-Dist: shapely==2.1.1; extra == 'pinned'
Requires-Dist: typing-extensions==4.15.0; (python_full_version < '3.13') and extra == 'pinned'
Requires-Dist: urllib3==2.5.0; extra == 'pinned'
Requires-Dist: yarl==1.20.1; extra == 'pinned'
